{
  "question": {
    "questionId": "1135",
    "questionFrontendId": "1045",
    "boundTopicId": null,
    "title": "Customers Who Bought All Products",
    "titleSlug": "customers-who-bought-all-products",
    "content": null,
    "translatedTitle": null,
    "translatedContent": null,
    "isPaidOnly": true,
    "difficulty": "Medium",
    "likes": 26,
    "dislikes": 1,
    "isLiked": null,
    "similarQuestions": "[]",
    "contributors": [],
    "langToValidPlayground": null,
    "topicTags": [],
    "companyTagStats": null,
    "codeSnippets": null,
    "stats": "{\"totalAccepted\": \"2.7K\", \"totalSubmission\": \"4.1K\", \"totalAcceptedRaw\": 2720, \"totalSubmissionRaw\": 4086, \"acRate\": \"66.6%\"}",
    "hints": [],
    "solution": null,
    "status": null,
    "sampleTestCase": "{\"headers\":{\"Customer\":[\"customer_id\",\"product_key\"],\"Product\":[\"product_key\"]},\"rows\":{\"Customer\":[[1,5],[2,6],[3,5],[3,6],[1,6]],\"Product\":[[5],[6]]}}",
    "metaData": "{\r\n  \"mysql\": [\r\n    \"Create table If Not Exists Customer (customer_id int, product_key int)\",\r\n    \"Create table Product (product_key int)\"\r\n  ],\r\n  \"mssql\": [\r\n    \"Create table Customer (customer_id int, product_key int)\",\r\n    \"Create table Product (product_key int)\"\r\n  ],\r\n  \"oraclesql\": [\r\n    \"Create table Customer (customer_id int, product_key int)\",\r\n    \"Create table Product (product_key int)\"\r\n  ],\r\n  \"database\": true\r\n}",
    "judgerAvailable": true,
    "judgeType": "large",
    "mysqlSchemas": [
      "Create table If Not Exists Customer (customer_id int, product_key int)",
      "Create table Product (product_key int)",
      "Truncate table Customer",
      "insert into Customer (customer_id, product_key) values ('1', '5')",
      "insert into Customer (customer_id, product_key) values ('2', '6')",
      "insert into Customer (customer_id, product_key) values ('3', '5')",
      "insert into Customer (customer_id, product_key) values ('3', '6')",
      "insert into Customer (customer_id, product_key) values ('1', '6')",
      "Truncate table Product",
      "insert into Product (product_key) values ('5')",
      "insert into Product (product_key) values ('6')"
    ],
    "enableRunCode": true,
    "enableTestMode": false,
    "envInfo": "{\"mysql\": [\"MySQL\", \"<p>Run with <code>mysql-server 5.7.21</code>.</p>\"], \"mssql\": [\"MS SQL Server\", \"<p>Run with <code>mssql</code>.</p>\"], \"oraclesql\": [\"Oracle\", \"<p>Run with <code>oracle sql</code>.</p>\"]}",
    "libraryUrl": null,
    "__typename": "QuestionNode"
  }
}